{
    "Acceleration": 1,
    "CreationTime": "20210722T105655",
    "DoNotShowWindowOnFinish": false,
    "Events": [
        {
            "Delta": 0,
            "EventType": "MouseDown",
            "Timestamp": 500,
            "X": 85.37362491256339,
            "Y": 69.70756432202883
        },
        {
            "Delta": 0,
            "EventType": "MouseUp",
            "Timestamp": 530,
            "X": 85.37362491256339,
            "Y": 69.70756432202883
        },
        {
            "Delta": 0,
            "EventType": "MouseDown",
            "Timestamp": 6530,
            "X": 86.5815365415164,
            "Y": 69.73696521072506
        },
        {
            "Delta": 0,
            "EventType": "MouseUp",
            "Timestamp": 6560,
            "X": 86.5815365415164,
            "Y": 69.73696521072506
        },
        {
            "Delta": 0,
            "EventType": "MouseDown",
            "Timestamp": 8620,
            "X": 86.45641773976476,
            "Y": 68.33938311330591
        },
        {
            "Delta": 0,
            "EventType": "MouseUp",
            "Timestamp": 8650,
            "X": 86.45641773976476,
            "Y": 68.33938311330591
        },
        {
            "Delta": 0,
            "EventType": "MouseDown",
            "Timestamp": 8950,
            "X": 9.22918570781993,
            "Y": 7.422020931008833
        },
        {
            "Delta": 0,
            "EventType": "MouseUp",
            "Timestamp": 8980,
            "X": 9.22918570781993,
            "Y": 7.422020931008833
        },
        {
            "Delta": 0,
            "EventType": "MouseDown",
            "Timestamp": 10980,
            "X": 50.315137922197465,
            "Y": 5.343333613566683
        },
        {
            "Delta": 0,
            "EventType": "MouseUp",
            "Timestamp": 11010,
            "X": 50.315137922197465,
            "Y": 5.343333613566683
        }
    ],
    "LoopDuration": 0,
    "LoopInterval": 0,
    "LoopIterations": 1,
    "LoopType": "UntilStopped",
    "MacroSchemaVersion": 2,
    "RestartPlayer": false,
    "RestartPlayerAfterMinutes": 60
}